dmps/__init__.py
dmps/__main__.py
dmps/cache.py
dmps/cli.py
dmps/engine.py
dmps/error_handler.py
dmps/evaluation.py
dmps/formatters.py
dmps/intent.py
dmps/main.py
dmps/observability.py
dmps/optimizer.py
dmps/profiler.py
dmps/rbac.py
dmps/repl.py
dmps/schema.py
dmps/security.py
dmps/techniques.py
dmps/threat_model.py
dmps/token_tracker.py
dmps/validation.py
dmps-0.2.1.dist-info/licenses/LICENSE
dmps-0.2.1.dist-info/METADATA
dmps-0.2.1.dist-info/WHEEL
dmps-0.2.1.dist-info/entry_points.txt
dmps-0.2.1.dist-info/top_level.txt
dmps-0.2.1.dist-info/RECORD
