Metadata-Version: 2.4
Name: dmps
Version: 0.2.1
Summary: Dual-Mode Prompt System for AI prompt optimization using 4-D methodology
Home-page: https://github.com/MrBinnacle/dmps
Author: MrBinnacle
Author-email: MrBinnacle <noreply@dmps-project.org>
License: MIT
Project-URL: Homepage, https://github.com/MrBinnacle/dmps
Project-URL: Repository, https://github.com/MrBinnacle/dmps
Project-URL: Issues, https://github.com/MrBinnacle/dmps/issues
Classifier: Development Status :: 4 - Beta
Classifier: Intended Audience :: Developers
Classifier: License :: OSI Approved :: MIT License
Classifier: Programming Language :: Python :: 3
Classifier: Programming Language :: Python :: 3.8
Classifier: Programming Language :: Python :: 3.9
Classifier: Programming Language :: Python :: 3.10
Classifier: Programming Language :: Python :: 3.11
Classifier: Topic :: Software Development :: Libraries :: Python Modules
Classifier: Topic :: Scientific/Engineering :: Artificial Intelligence
Requires-Python: >=3.8
License-File: LICENSE
Provides-Extra: dev
Requires-Dist: black; extra == "dev"
Requires-Dist: flake8; extra == "dev"
Requires-Dist: isort; extra == "dev"
Requires-Dist: mypy; extra == "dev"
Requires-Dist: pre-commit; extra == "dev"
Requires-Dist: pytest; extra == "dev"
Requires-Dist: bandit; extra == "dev"
Requires-Dist: safety; extra == "dev"
Requires-Dist: autoflake; extra == "dev"
Requires-Dist: autopep8; extra == "dev"
Dynamic: license-file
